src/CHG_cal.py
src/__init__.py
src/wfn_export.py
wfn_plot/CHG_cal.py
wfn_plot/__init__.py
wfn_plot/chg_cal.py
wfn_plot/wfn_export.py
wfn_plot-0.1.2.dist-info/METADATA
wfn_plot-0.1.2.dist-info/WHEEL
wfn_plot-0.1.2.dist-info/entry_points.txt
wfn_plot-0.1.2.dist-info/top_level.txt
wfn_plot-0.1.2.dist-info/RECORD
